fang/__init__.py
fang/calc.py
zxf_module-0.0.1.dist-info/METADATA
zxf_module-0.0.1.dist-info/WHEEL
zxf_module-0.0.1.dist-info/top_level.txt
zxf_module-0.0.1.dist-info/RECORD
