Metadata-Version: 2.1
Name: zxf-module
Version: 0.0.1
Summary: 简单的加减运算上传测试
Home-page: https://www.baidu.com
Author: Xiaofang
Author-email: 1958976685@qq.com
